os2024/__cli__.py
os2024/__init__.py
os2024/_version.py
os2024/book/_config.yml
os2024/book/_toc.yml
os2024/book/about/contributors.md
os2024/book/about/contributors.png
os2024/book/about/index.md
os2024/book/assets/assets/extra/.gitkeep
os2024/book/assets/extra/.gitkeep
os2024/book/index.md
os2024/book/projects/202021029/homework-w2.md
os2024/book/projects/202021029/homework-w3.md
os2024/book/projects/202021029/index.md
os2024/book/projects/202121006/code
os2024/book/projects/202121006/hw-wk02.md
os2024/book/projects/202121006/hw-wk03.md
os2024/book/projects/202121006/hw-wk04.md
os2024/book/projects/202121006/hw-wk06.md
os2024/book/projects/202121006/hw-wk07.md
os2024/book/projects/202121006/index.md
os2024/book/projects/202121006/input.txt
os2024/book/projects/202121010/homework.md
os2024/book/projects/202121010/index.md
os2024/book/projects/202121010/kv_store/database.txt
os2024/book/projects/202121010/kv_store/kv_store.c
os2024/book/projects/202221014/hw-wk02.md
os2024/book/projects/202221014/hw-wk03.md
os2024/book/projects/202221014/hw-wk04.md
os2024/book/projects/202221014/hw-wk06.md
os2024/book/projects/202221014/hw-wk07.md
os2024/book/projects/202221014/index.md
os2024/book/projects/202221014/kv_store/Makefile
os2024/book/projects/202221014/kv_store/database.txt
os2024/book/projects/202221014/kv_store/kv_store
os2024/book/projects/202221014/kv_store/src/kv_store.c
os2024/book/projects/202221014/kv_store/src/kv_store.h
os2024/book/projects/202221014/kv_store/src/main.c
os2024/book/projects/202221014/project_manual.md
os2024/book/projects/202321007/index.md
os2024/book/projects/202321010/hw_wk02.md
os2024/book/projects/202321010/hw_wk03.md
os2024/book/projects/202321010/hw_wk04.md
os2024/book/projects/202321010/hw_wk06.md
os2024/book/projects/202321010/hw_wk07.md
os2024/book/projects/202321010/index.md
os2024/book/projects/202321010/reverse/reverse.c
os2024/book/projects/202321017/grep.c
os2024/book/projects/202321017/hw-wk02.md
os2024-0.10.0.dist-info/LICENSE
os2024-0.10.0.dist-info/METADATA
os2024-0.10.0.dist-info/WHEEL
os2024-0.10.0.dist-info/entry_points.txt
os2024-0.10.0.dist-info/RECORD
